huaweicloudsdkclouddeploy/__init__.py
huaweicloudsdkclouddeploy/v2/__init__.py
huaweicloudsdkclouddeploy/v2/clouddeploy_async_client.py
huaweicloudsdkclouddeploy/v2/clouddeploy_client.py
huaweicloudsdkclouddeploy/v2/model/__init__.py
huaweicloudsdkclouddeploy/v2/model/app_component_dao.py
huaweicloudsdkclouddeploy/v2/model/config_info_do.py
huaweicloudsdkclouddeploy/v2/model/create_deploy_task_by_template_request.py
huaweicloudsdkclouddeploy/v2/model/create_deploy_task_by_template_response.py
huaweicloudsdkclouddeploy/v2/model/create_deployment_group_request.py
huaweicloudsdkclouddeploy/v2/model/create_deployment_group_response.py
huaweicloudsdkclouddeploy/v2/model/create_deployment_host_request.py
huaweicloudsdkclouddeploy/v2/model/create_deployment_host_response.py
huaweicloudsdkclouddeploy/v2/model/delete_deploy_task_request.py
huaweicloudsdkclouddeploy/v2/model/delete_deploy_task_response.py
huaweicloudsdkclouddeploy/v2/model/delete_deployment_group_request.py
huaweicloudsdkclouddeploy/v2/model/delete_deployment_group_response.py
huaweicloudsdkclouddeploy/v2/model/delete_deployment_host_request.py
huaweicloudsdkclouddeploy/v2/model/delete_deployment_host_response.py
huaweicloudsdkclouddeploy/v2/model/deployment_group.py
huaweicloudsdkclouddeploy/v2/model/deployment_group_detail.py
huaweicloudsdkclouddeploy/v2/model/deployment_group_update_request.py
huaweicloudsdkclouddeploy/v2/model/deployment_host.py
huaweicloudsdkclouddeploy/v2/model/deployment_host_authorization_body.py
huaweicloudsdkclouddeploy/v2/model/deployment_host_detail.py
huaweicloudsdkclouddeploy/v2/model/deployment_host_info.py
huaweicloudsdkclouddeploy/v2/model/deployment_host_request.py
huaweicloudsdkclouddeploy/v2/model/deployment_update_host.py
huaweicloudsdkclouddeploy/v2/model/dynamic_config_info.py
huaweicloudsdkclouddeploy/v2/model/env_execution_body.py
huaweicloudsdkclouddeploy/v2/model/execute_record_v2_body.py
huaweicloudsdkclouddeploy/v2/model/key_value_do.py
huaweicloudsdkclouddeploy-3.1.43.dist-info/LICENSE
huaweicloudsdkclouddeploy-3.1.43.dist-info/METADATA
huaweicloudsdkclouddeploy-3.1.43.dist-info/WHEEL
huaweicloudsdkclouddeploy-3.1.43.dist-info/top_level.txt
huaweicloudsdkclouddeploy-3.1.43.dist-info/RECORD
