Metadata-Version: 2.1
Name: huaweicloudsdkclouddeploy
Version: 3.1.43
Summary: CloudDeploy
Home-page: https://github.com/huaweicloud/huaweicloud-sdk-python-v3
Author: HuaweiCloud SDK
Author-email: hwcloudsdk@huawei.com
License: Apache LICENSE 2.0
Keywords: huaweicloud,sdk,CloudDeploy
Classifier: Development Status :: 5 - Production/Stable
Classifier: Intended Audience :: Developers
Classifier: License :: OSI Approved :: Apache Software License
Classifier: Programming Language :: Python :: 2.7
Classifier: Programming Language :: Python :: 3.3
Classifier: Programming Language :: Python :: 3.4
Classifier: Programming Language :: Python :: 3.5
Classifier: Programming Language :: Python :: 3.6
Classifier: Programming Language :: Python :: 3.7
Classifier: Programming Language :: Python :: 3.8
Classifier: Programming Language :: Python :: 3.9
Classifier: Topic :: Software Development
Requires-Python: >=2.7,!=3.0.*,!=3.1.*,!=3.2.*
License-File: LICENSE
Requires-Dist: huaweicloudsdkcore (>=3.1.43)
